Metadata-Version: 2.1
Name: flax-gated-linear-rnn
Version: 1.0.3
Summary: GatedLinearRNN Model
Home-page: https://github.com/tobiaskatsch/GatedLinearRNN
Author: Tobias Katsch
Author-email: tobias.katsch42@gmail.com
License: Apache License, Version 2.0
Requires-Python: >=3.7
License-File: LICENSE.txt
Requires-Dist: jax >=0.4.20
Requires-Dist: flax >=0.8.0
